subsplease_rss/__init__.py
subsplease_rss/rss.py
subsplease_rss-0.1.0.dist-info/WHEEL
subsplease_rss-0.1.0.dist-info/METADATA
subsplease_rss-0.1.0.dist-info/RECORD
