Metadata-Version: 2.1
Name: subsplease-rss
Version: 0.1.0
Summary: SubsPlease RSS Helper
Author: SlavWolf
Author-email: git@slavwolf.dev
Requires-Python: >=3.10,<3.11
Classifier: Programming Language :: Python :: 3
Classifier: Programming Language :: Python :: 3.10
Requires-Dist: feedparser (>=6.0.10,<7.0.0)
Requires-Dist: requests (>=2.27.1,<3.0.0)
